sispagtoolkit/__init__.py
sispagtoolkit/cnab240/__init__.py
sispagtoolkit/cnab240/liquidacao_boletos.py
sispagtoolkit/cnab240/liquidacao_qrcode.py
sispagtoolkit/cnab240/pagamento_concessionaria.py
sispagtoolkit/cnab240/pagamentos_cheque_ted_op.py
sispagtoolkit/cnab240/pagamentos_pix.py
sispagtoolkit/cnab240/pagamentos_tef.py
sispagtoolkit/cnab240/lotes/__init__.py
sispagtoolkit/cnab240/lotes/arquivo/__init__.py
sispagtoolkit/cnab240/lotes/arquivo/arquivo.py
sispagtoolkit/cnab240/lotes/arquivo/head_arquivo.py
sispagtoolkit/cnab240/lotes/arquivo/trailer_arquivo.py
sispagtoolkit/cnab240/lotes/liquidacao_boletos_qrcode/__init__.py
sispagtoolkit/cnab240/lotes/liquidacao_boletos_qrcode/segmentos/__init__.py
sispagtoolkit/cnab240/lotes/liquidacao_boletos_qrcode/segmentos/head_lote.py
sispagtoolkit/cnab240/lotes/liquidacao_boletos_qrcode/segmentos/segmento_j.py
sispagtoolkit/cnab240/lotes/liquidacao_boletos_qrcode/segmentos/segmento_j52.py
sispagtoolkit/cnab240/lotes/liquidacao_boletos_qrcode/segmentos/segmento_j52pix.py
sispagtoolkit/cnab240/lotes/liquidacao_boletos_qrcode/segmentos/trailer_lote.py
sispagtoolkit/cnab240/lotes/pagamentos_concessionarias_tributos/__init__.py
sispagtoolkit/cnab240/lotes/pagamentos_concessionarias_tributos/segmentos/__init__.py
sispagtoolkit/cnab240/lotes/pagamentos_concessionarias_tributos/segmentos/head_lote.py
sispagtoolkit/cnab240/lotes/pagamentos_concessionarias_tributos/segmentos/segmento_o.py
sispagtoolkit/cnab240/lotes/pagamentos_concessionarias_tributos/segmentos/trailer_lote.py
sispagtoolkit/cnab240/lotes/pagamentos_e_transferencias/__init__.py
sispagtoolkit/cnab240/lotes/pagamentos_e_transferencias/segmentos/__init__.py
sispagtoolkit/cnab240/lotes/pagamentos_e_transferencias/segmentos/head_lote.py
sispagtoolkit/cnab240/lotes/pagamentos_e_transferencias/segmentos/segmento_a.py
sispagtoolkit/cnab240/lotes/pagamentos_e_transferencias/segmentos/segmento_b.py
sispagtoolkit-0.1.3.dist-info/licenses/LICENSE
sispagtoolkit-0.1.3.dist-info/METADATA
sispagtoolkit-0.1.3.dist-info/WHEEL
sispagtoolkit-0.1.3.dist-info/top_level.txt
sispagtoolkit-0.1.3.dist-info/RECORD
