Metadata-Version: 2.4
Name: SispagToolKit
Version: 0.1.3
Summary: Biblioteca para geração de remessas de pagamento CNAB240 baseada para o sistema SISPAG da instituição Itaú.
Home-page: https://github.com/LukaOliveira/sispagtoolkit
Author: Pedro Luka Oliveira
Author-email: pedrolukaoliveira@protonmail.com
Classifier: Programming Language :: Python :: 3
Classifier: License :: OSI Approved :: MIT License
Classifier: Operating System :: OS Independent
Requires-Python: >=3.6
License-File: LICENSE
Dynamic: author
Dynamic: author-email
Dynamic: classifier
Dynamic: description
Dynamic: description-content-type
Dynamic: home-page
Dynamic: license-file
Dynamic: requires-python
Dynamic: summary
